py365/__init__.py
py365/graph365.py
py365/py365.py
py365/api/__init__.py
py365/api/invitation_manager.py
py365/api/users.py
py365/apis/__init__.py
py365/apis/invitation_manager.py
py365/apis/users.py
py365/auth/__init__.py
py365/auth/app_connection.py
py365/enums/__init__.py
py365/enums/body_type.py
py365/enums/enums.py
py365/enums/invitation_status_values.py
py365/enums/invited_user_types.py
py365/resources/__init__.py
py365/resources/_base_resource.py
py365/resources/assigned_license.py
py365/resources/email_address.py
py365/resources/invitation.py
py365/resources/invited_user_message_info.py
py365/resources/password_profile.py
py365/resources/recipient.py
py365/resources/user.py
py365/rsc/__init__.py
py365/rsc/_base_resource.py
py365/rsc/assigned_license.py
py365/rsc/email_address.py
py365/rsc/invitation.py
py365/rsc/invited_user_message_info.py
py365/rsc/item_body.py
py365/rsc/message.py
py365/rsc/password_profile.py
py365/rsc/recipient.py
py365/rsc/user.py
py365-0.1.2.dist-info/LICENSE
py365-0.1.2.dist-info/METADATA
py365-0.1.2.dist-info/WHEEL
py365-0.1.2.dist-info/top_level.txt
py365-0.1.2.dist-info/RECORD
