Metadata-Version: 2.1
Name: py365
Version: 0.1.2
Summary: Python Library for App Development over MS Graph365 
Home-page: https://github.com/dudil/py365
Author: Dudi Levy
Author-email: dudil@users.noreply.github.com
License: MIT
Platform: UNKNOWN
Classifier: License :: OSI Approved :: MIT License
Classifier: Programming Language :: Python :: 3
Classifier: Operating System :: OS Independent
Classifier: Development Status :: 3 - Alpha
Requires-Python: >=3.6
Requires-Dist: adal (>=1.2.1)
Requires-Dist: requests (>=2.21.0)
Requires-Dist: urllib3 (>=1.24.2)
